archean/__init__.py
archean/__main__.py
archean/cleanup.py
archean/db_writer.py
archean/wiki_downloader.py
archean/wiki_reader.py
archean-3.1.0.dist-info/entry_points.txt
archean-3.1.0.dist-info/LICENSE
archean-3.1.0.dist-info/WHEEL
archean-3.1.0.dist-info/METADATA
archean-3.1.0.dist-info/RECORD
