Metadata-Version: 2.1
Name: archean
Version: 3.1.0
Summary: Extract Information from Wikimedia Dumps
Home-page: https://gitlab.com/thisisayushg/archean
License: LICENSE
Author: Ayush Gupta
Author-email: 4c4ddc00-742a-4213-8e40-59a5e3b0fbb1@archean.anonaddy.com
Requires-Python: >=3.6.2,<4.0.0
Classifier: License :: OSI Approved :: MIT License
Classifier: License :: Other/Proprietary License
Classifier: Programming Language :: Python :: 3
Classifier: Programming Language :: Python :: 3.10
Classifier: Programming Language :: Python :: 3.6
Classifier: Programming Language :: Python :: 3.7
Classifier: Programming Language :: Python :: 3.8
Classifier: Programming Language :: Python :: 3.9
Requires-Dist: bs4 (>=0.0.1,<0.0.2)
Requires-Dist: mwparserfromhell (>=0.6.3,<0.7.0)
Requires-Dist: pymongo (>=3.12.0,<4.0.0)
Requires-Dist: requests (>=2.26.0,<3.0.0)
Requires-Dist: rich (>=10.16.2,<11.0.0)
Requires-Dist: tqdm (>=4.62.2,<5.0.0)
Project-URL: Repository, https://gitlab.com/thisisayushg/archean
